{
  "header": {
    "home": "Home",
    "languageSelection": "Select language",
    "login": "Access my account",
    "theme": {
      "lightMode": "Switch to Light Mode",
      "darkMode": "Switch to Dark Mode"
    }
  },
  "footer": {
    "copyrightNotice": "All rights reserved",
    "credits": "Carefully crafted by"
  },
  "homePage": {
    "features": {
      "title": "Features",
      "items": [
        {
          "title": "Personalized Learning",
          "description": "Paths adapted to your needs"
        },
        {
          "title": "Smart Learning",
          "description": "AI-powered learning recommendations"
        },
        {
          "title": "Global Collaboration",
          "description": "Connect with learners worldwide"
        },
        {
          "title": "Rich Resources",
          "description": "Access a diverse library of content"
        }
      ]
    }
  },
  "auth": {
    "common": {
      "emailLabel": "Email",
      "backToLogin": "Back to login",
      "backToHome": "Back to Home",
      "resetButton": "Recevoir un lien"
    },
    "login": {
      "welcomeMessage": "Welcome to your private space",
      "welcomeDescription": "An integrated information system that enables new school management methods.",
      "title": "Welcome to your private space",
      "description": "Sign in to your account",
      "identifierLabel": "Identifier",
      "passwordLabel": "Password",
      "rememberMe": "Keep me signed in",
      "submitButton": "SIGN IN",
      "forgotPassword": "Forgot password?"
    },
    "forgotPassword": {
      "title": "Forgot password",
      "description": "Enter your email to reset your password"
    },
    "newPassword": {
      "title": "New password",
      "description": "Create your new password",
      "newPasswordLabel": "New password",
      "confirmPasswordLabel": "Confirm password",
      "submitButton": "RESET PASSWORD"
    }
  },
  "cvPage": {
    "title": "CV PAGE",
    "welcome": "Welcome back!"
  },
  "invoicePage": {
    "title": "INVOICE PAGE",
    "welcome": "Welcome back!"
  },
  "notFound": {
    "title": "Page not found",
    "description": "Sorry, the page you are looking for does not exist.",
    "backHome": "Back to home"
  }
}
